room_heater/__init__.py
room_heater/__main__.py
room_heater/heater.py
room_heater-0.0.2.dist-info/licenses/LICENSE
room_heater-0.0.2.dist-info/METADATA
room_heater-0.0.2.dist-info/WHEEL
room_heater-0.0.2.dist-info/entry_points.txt
room_heater-0.0.2.dist-info/top_level.txt
room_heater-0.0.2.dist-info/RECORD
